LICENSE
MANIFEST.in
README.md
setup.py
grispy/__init__.py
grispy/core.py
grispy/distances.py
grispy/validators.py
grispy.egg-info/PKG-INFO
grispy.egg-info/SOURCES.txt
grispy.egg-info/dependency_links.txt
grispy.egg-info/requires.txt
grispy.egg-info/top_level.txt