Metadata-Version: 2.1
Name: grispy
Version: 0.2.0
Summary: Grid Search in Python
Home-page: https://github.com/mchalela/GriSPy
Author: ['Martin Chalela', 'Emanuel Sillero', 'Luis Pereyra', 'Alejandro Garcia', 'Juan B. Cabral']
Author-email: tinchochalela@gmail.com
License: MIT
Keywords: grispy,nearest,neighbors,search,grid
Platform: UNKNOWN
Classifier: Development Status :: 4 - Beta
Classifier: Intended Audience :: Education
Classifier: Intended Audience :: Science/Research
Classifier: License :: OSI Approved :: MIT License
Classifier: Operating System :: OS Independent
Classifier: Programming Language :: Python
Classifier: Programming Language :: Python :: 3.8
Classifier: Programming Language :: Python :: Implementation :: CPython
Classifier: Topic :: Scientific/Engineering
